hkex_tools.py
hkex_tools-0.0.1.dist-info/License.txt
hkex_tools-0.0.1.dist-info/METADATA
hkex_tools-0.0.1.dist-info/WHEEL
hkex_tools-0.0.1.dist-info/top_level.txt
hkex_tools-0.0.1.dist-info/RECORD
